fmdt_videos/__init__.py
fmdt_videos-0.0.1.dist-info/METADATA
fmdt_videos-0.0.1.dist-info/WHEEL
fmdt_videos-0.0.1.dist-info/RECORD
