Metadata-Version: 2.1
Name: fmdt-videos
Version: 0.0.1
Summary: videos for fast meteor detection toolbox
Project-URL: fmdt, https://github.com/alsoc/fmdt
Project-URL: Homepage, https://github.com/ejovo13/fmdt_scripts
Author-email: Evan Voyles <ejovo13@yahoo.com>
Classifier: License :: OSI Approved :: MIT License
Classifier: Operating System :: OS Independent
Classifier: Programming Language :: Python :: 3
Requires-Python: >=3.10
